phiera/__init__.py
phiera/backends.py
phiera/exceptions.py
phiera/phiera.py
phiera/util.py
phiera-2.1.0.dist-info/LICENSE.md
phiera-2.1.0.dist-info/METADATA
phiera-2.1.0.dist-info/WHEEL
phiera-2.1.0.dist-info/RECORD
