Metadata-Version: 2.1
Name: phiera
Version: 2.1.0
Summary: a python hiera parser
Home-page: https://github.com/Nike-Inc/phiera
License: Apache 2.0
Author: Andrei Zbikowski, Rob King
Maintainer: Mohamed Abdul Huq Ismail
Maintainer-email: Abdul.Ismail@nike.com
Requires-Python: >=3.10.10,<4.0.0
Classifier: License :: Other/Proprietary License
Classifier: Programming Language :: Python :: 3
Classifier: Programming Language :: Python :: 3.11
Requires-Dist: PyYAML (>=6.0.0,<7.0.0)
Project-URL: Repository, https://github.com/Nike-Inc/phiera
